{
	"song": {
		"player1": "bf",
		"player2": "UArem1",
		"notes": [
			{
				"lengthInSteps": 16,
				"sectionNotes": [],
				"mustHitSection": false
			},
			{
				"lengthInSteps": 16,
				"sectionNotes": [],
				"mustHitSection": true
			},
			{
				"lengthInSteps": 16,
				"sectionNotes": [],
				"mustHitSection": false
			},
			{
				"lengthInSteps": 20,
				"sectionNotes": [
					[
						7565.21739130435,
						3,
						0
					],
					[
						7304.34782608696,
						3,
						0
					],
					[
						8086.95652173913,
						0,
						0
					],
					[
						7826.08695652174,
						0,
						0
					]
				],
				"gfSection": false,
				"mustHitSection": false
			},
			{
				"lengthInSteps": 16,
				"sectionNotes": [
					[
						8347.82608695652,
						2,
						0
					],
					[
						8608.69565217391,
						2,
						0
					],
					[
						8869.5652173913,
						1,
						130.434782608696
					],
					[
						9391.30434782609,
						2,
						0
					],
					[
						9652.17391304348,
						2,
						0
					],
					[
						9913.04347826087,
						1,
						0
					],
					[
						10173.9130434783,
						1,
						0
					]
				],
				"mustHitSection": false
			},
			{
				"lengthInSteps": 16,
				"sectionNotes": [
					[
						10434.7826086957,
						4,
						0
					],
					[
						10695.652173913,
						4,
						0
					],
					[
						10956.5217391304,
						5,
						130.434782608696
					],
					[
						11478.2608695652,
						3,
						0
					],
					[
						11739.1304347826,
						3,
						0
					],
					[
						12000,
						0,
						0
					],
					[
						12260.8695652174,
						0,
						0
					]
				],
				"mustHitSection": true
			},
			{
				"lengthInSteps": 16,
				"sectionNotes": [
					[
						12521.7391304348,
						2,
						0
					],
					[
						12782.6086956522,
						2,
						0
					],
					[
						13043.4782608696,
						1,
						130.434782608696
					],
					[
						13565.2173913043,
						1,
						0
					],
					[
						13826.0869565217,
						1,
						0
					],
					[
						14086.9565217391,
						2,
						0
					],
					[
						14347.8260869565,
						2,
						0
					]
				],
				"mustHitSection": true
			},
			{
				"lengthInSteps": 16,
				"sectionNotes": [
					[
						14608.6956521739,
						5,
						0
					],
					[
						14869.5652173913,
						5,
						0
					],
					[
						15130.4347826087,
						4,
						130.434782608696
					],
					[
						15652.1739130435,
						2,
						0
					],
					[
						15913.0434782609,
						2,
						0
					],
					[
						16173.9130434783,
						1,
						0
					],
					[
						16304.347826087,
						1,
						0
					],
					[
						16235.8695652174,
						2,
						0
					],
					[
						16363.0434782609,
						2,
						130.434782608696
					]
				],
				"mustHitSection": false
			},
			{
				"lengthInSteps": 16,
				"sectionNotes": [
					[
						16695.652173913,
						3,
						0
					],
					[
						16695.652173913,
						0,
						0
					],
					[
						16956.5217391304,
						0,
						0
					],
					[
						16956.5217391304,
						3,
						0
					],
					[
						17217.3913043478,
						2,
						260.869565217391
					],
					[
						17739.1304347826,
						3,
						0
					],
					[
						17869.5652173913,
						1,
						0
					],
					[
						18000,
						3,
						0
					],
					[
						18130.4347826087,
						1,
						0
					],
					[
						18260.8695652174,
						2,
						130.434782608696
					],
					[
						18521.7391304348,
						2,
						130.434782608696
					]
				],
				"mustHitSection": false
			},
			{
				"lengthInSteps": 16,
				"sectionNotes": [
					[
						18782.6086956522,
						7,
						260.869565217391
					],
					[
						18782.6086956522,
						2,
						0
					],
					[
						19043.4782608696,
						2,
						0
					],
					[
						19304.347826087,
						1,
						0
					],
					[
						19434.7826086957,
						1,
						0
					],
					[
						19363.0434782609,
						2,
						0
					],
					[
						19493.4782608696,
						2,
						130.434782608696
					],
					[
						19826.0869565217,
						1,
						0
					],
					[
						20086.9565217391,
						1,
						0
					],
					[
						20347.8260869565,
						1,
						260.869565217391
					]
				],
				"mustHitSection": true
			},
			{
				"lengthInSteps": 16,
				"sectionNotes": [
					[
						20869.5652173913,
						5,
						0
					],
					[
						21000,
						7,
						0
					],
					[
						21130.4347826087,
						5,
						0
					],
					[
						21260.8695652174,
						7,
						0
					],
					[
						21391.3043478261,
						6,
						130.434782608696
					],
					[
						21652.1739130435,
						6,
						130.434782608696
					],
					[
						21913.0434782609,
						6,
						260.869565217391
					],
					[
						22434.7826086957,
						2,
						130.434782608696
					],
					[
						22826.0869565217,
						3,
						130.434782608696
					]
				],
				"mustHitSection": false
			},
			{
				"lengthInSteps": 16,
				"sectionNotes": [
					[
						23217.3913043478,
						2,
						130.434782608696
					],
					[
						23608.6956521739,
						3,
						130.434782608696
					],
					[
						24000,
						2,
						130.434782608696
					],
					[
						24260.8695652174,
						1,
						130.434782608696
					],
					[
						24521.7391304348,
						2,
						0
					],
					[
						24782.6086956522,
						2,
						0
					]
				],
				"mustHitSection": false
			},
			{
				"lengthInSteps": 16,
				"sectionNotes": [
					[
						25043.4782608696,
						5,
						0
					],
					[
						25304.347826087,
						5,
						0
					],
					[
						25434.7826086957,
						7,
						0
					],
					[
						25565.2173913044,
						5,
						0
					],
					[
						25826.0869565217,
						5,
						0
					],
					[
						26608.6956521739,
						1,
						130.434782608696
					],
					[
						27000,
						0,
						130.434782608696
					],
					[
						26086.9565217391,
						5,
						391.304347826087
					]
				],
				"mustHitSection": true
			},
			{
				"lengthInSteps": 16,
				"sectionNotes": [
					[
						27391.3043478261,
						1,
						130.434782608696
					],
					[
						28173.9130434783,
						1,
						130.434782608696
					],
					[
						28434.7826086957,
						0,
						130.434782608696
					],
					[
						27782.6086956522,
						0,
						130.434782608696
					],
					[
						28695.6521739131,
						2,
						0
					],
					[
						28956.5217391304,
						2,
						0
					]
				],
				"mustHitSection": true
			},
			{
				"lengthInSteps": 16,
				"sectionNotes": [
					[
						29217.3913043478,
						7,
						0
					],
					[
						29478.2608695652,
						7,
						0
					],
					[
						29608.6956521739,
						5,
						0
					],
					[
						29739.1304347826,
						4,
						0
					],
					[
						30000,
						4,
						0
					],
					[
						30260.8695652174,
						4,
						391.304347826087
					],
					[
						30782.6086956522,
						1,
						130.434782608696
					],
					[
						31173.9130434783,
						3,
						130.434782608696
					]
				],
				"mustHitSection": false
			},
			{
				"lengthInSteps": 16,
				"sectionNotes": [
					[
						31826.0869565218,
						1,
						130.434782608696
					],
					[
						32217.3913043478,
						0,
						130.434782608696
					],
					[
						32869.5652173913,
						1,
						130.434782608696
					],
					[
						33260.8695652174,
						3,
						130.434782608696
					]
				],
				"mustHitSection": false
			},
			{
				"lengthInSteps": 16,
				"sectionNotes": [
					[
						33913.0434782609,
						5,
						130.434782608696
					],
					[
						34304.347826087,
						6,
						130.434782608696
					],
					[
						34434.7826086957,
						0,
						130.434782608696
					],
					[
						34826.0869565218,
						0,
						130.434782608696
					]
				],
				"mustHitSection": true
			},
			{
				"lengthInSteps": 16,
				"sectionNotes": [
					[
						35478.2608695652,
						0,
						130.434782608696
					],
					[
						35869.5652173913,
						0,
						130.434782608696
					],
					[
						36521.7391304348,
						2,
						130.434782608696
					],
					[
						36913.0434782609,
						2,
						130.434782608696
					]
				],
				"mustHitSection": true
			},
			{
				"lengthInSteps": 16,
				"sectionNotes": [
					[
						37565.2173913044,
						6,
						130.434782608696
					],
					[
						37956.5217391304,
						6,
						130.434782608696
					],
					[
						38608.6956521739,
						2,
						0
					],
					[
						38677.1739130435,
						3,
						0
					],
					[
						38739.1304347826,
						2,
						0
					],
					[
						38804.347826087,
						1,
						0
					],
					[
						38859.7826086957,
						0,
						0
					],
					[
						38931.5217391304,
						1,
						0
					],
					[
						38986.9565217391,
						2,
						0
					],
					[
						39055.4347826087,
						3,
						0
					],
					[
						39130.4347826087,
						2,
						0
					],
					[
						39195.652173913,
						1,
						0
					],
					[
						39254.347826087,
						0,
						0
					],
					[
						39326.0869565217,
						1,
						0
					]
				],
				"mustHitSection": false
			},
			{
				"lengthInSteps": 16,
				"sectionNotes": [
					[
						40695.652173913,
						2,
						0
					],
					[
						40764.1304347826,
						3,
						0
					],
					[
						40826.0869565217,
						2,
						0
					],
					[
						40891.3043478261,
						1,
						0
					],
					[
						40946.7391304348,
						0,
						0
					],
					[
						41018.4782608696,
						1,
						0
					],
					[
						41073.9130434783,
						2,
						0
					],
					[
						41142.3913043478,
						3,
						0
					],
					[
						41217.3913043478,
						2,
						0
					],
					[
						41282.6086956522,
						1,
						0
					],
					[
						41341.3043478261,
						0,
						0
					],
					[
						41413.0434782609,
						1,
						0
					],
					[
						39652.1739130435,
						2,
						0
					],
					[
						39782.6086956522,
						2,
						0
					],
					[
						39720.652173913,
						3,
						0
					],
					[
						39841.3043478261,
						1,
						0
					],
					[
						39896.7391304348,
						0,
						0
					],
					[
						39968.4782608696,
						1,
						0
					],
					[
						40023.9130434783,
						2,
						0
					],
					[
						40092.3913043478,
						3,
						0
					],
					[
						40154.347826087,
						2,
						0
					],
					[
						40219.5652173913,
						1,
						0
					],
					[
						40275,
						0,
						0
					],
					[
						40346.7391304348,
						1,
						0
					]
				],
				"mustHitSection": false
			},
			{
				"lengthInSteps": 16,
				"sectionNotes": [
					[
						42782.6086956522,
						2,
						0
					],
					[
						42851.0869565217,
						3,
						0
					],
					[
						42913.0434782609,
						2,
						0
					],
					[
						42978.2608695652,
						1,
						0
					],
					[
						43033.6956521739,
						0,
						0
					],
					[
						43105.4347826087,
						1,
						0
					],
					[
						43160.8695652174,
						2,
						0
					],
					[
						43229.347826087,
						3,
						0
					],
					[
						43304.347826087,
						2,
						0
					],
					[
						43369.5652173913,
						1,
						0
					],
					[
						43428.2608695652,
						0,
						0
					],
					[
						43500,
						1,
						0
					],
					[
						41739.1304347826,
						6,
						0
					],
					[
						41869.5652173913,
						6,
						0
					],
					[
						41807.6086956522,
						7,
						0
					],
					[
						41928.2608695652,
						5,
						0
					],
					[
						41983.6956521739,
						4,
						0
					],
					[
						42055.4347826087,
						5,
						0
					],
					[
						42110.8695652174,
						6,
						0
					],
					[
						42179.347826087,
						7,
						0
					],
					[
						42241.3043478261,
						6,
						0
					],
					[
						42306.5217391304,
						5,
						0
					],
					[
						42361.9565217391,
						4,
						0
					],
					[
						42433.6956521739,
						5,
						0
					]
				],
				"mustHitSection": true
			},
			{
				"lengthInSteps": 16,
				"sectionNotes": [
					[
						44869.5652173913,
						2,
						0
					],
					[
						44938.0434782609,
						3,
						0
					],
					[
						45000,
						2,
						0
					],
					[
						45065.2173913044,
						1,
						0
					],
					[
						45120.652173913,
						0,
						0
					],
					[
						45192.3913043478,
						1,
						0
					],
					[
						45247.8260869565,
						2,
						0
					],
					[
						45316.3043478261,
						3,
						0
					],
					[
						45391.3043478261,
						2,
						0
					],
					[
						45456.5217391304,
						1,
						0
					],
					[
						45515.2173913044,
						0,
						0
					],
					[
						45586.9565217391,
						1,
						0
					],
					[
						43826.0869565217,
						2,
						0
					],
					[
						43956.5217391304,
						2,
						0
					],
					[
						43894.5652173913,
						3,
						0
					],
					[
						44015.2173913044,
						1,
						0
					],
					[
						44070.652173913,
						0,
						0
					],
					[
						44142.3913043478,
						1,
						0
					],
					[
						44197.8260869565,
						2,
						0
					],
					[
						44266.3043478261,
						3,
						0
					],
					[
						44328.2608695652,
						2,
						0
					],
					[
						44393.4782608696,
						1,
						0
					],
					[
						44448.9130434783,
						0,
						0
					],
					[
						44520.652173913,
						1,
						0
					]
				],
				"mustHitSection": true
			},
			{
				"lengthInSteps": 16,
				"sectionNotes": [
					[
						45913.0434782609,
						6,
						0
					],
					[
						46043.4782608696,
						6,
						0
					],
					[
						45981.5217391304,
						7,
						0
					],
					[
						46102.1739130435,
						5,
						0
					],
					[
						46157.6086956522,
						4,
						0
					],
					[
						46229.347826087,
						5,
						0
					],
					[
						46284.7826086957,
						6,
						0
					],
					[
						46353.2608695652,
						7,
						0
					],
					[
						46415.2173913044,
						6,
						0
					],
					[
						46480.4347826087,
						5,
						0
					],
					[
						46535.8695652174,
						4,
						0
					],
					[
						46607.6086956522,
						5,
						0
					],
					[
						46956.5217391304,
						2,
						0
					],
					[
						47086.9565217391,
						2,
						0
					],
					[
						47217.3913043478,
						2,
						0
					],
					[
						47347.8260869565,
						2,
						0
					],
					[
						47478.2608695652,
						3,
						0
					],
					[
						47608.6956521739,
						3,
						0
					],
					[
						47739.1304347826,
						3,
						0
					],
					[
						47869.5652173913,
						3,
						0
					]
				],
				"mustHitSection": false
			},
			{
				"lengthInSteps": 16,
				"sectionNotes": [
					[
						48000,
						1,
						0
					],
					[
						48130.4347826087,
						1,
						0
					],
					[
						48260.8695652174,
						1,
						0
					],
					[
						48391.3043478261,
						1,
						0
					],
					[
						48521.7391304348,
						0,
						391.304347826087
					],
					[
						49043.4782608696,
						1,
						0
					],
					[
						49173.9130434783,
						1,
						0
					],
					[
						49304.347826087,
						1,
						0
					],
					[
						49434.7826086956,
						1,
						0
					],
					[
						49565.2173913043,
						2,
						0
					],
					[
						49695.652173913,
						2,
						0
					],
					[
						49826.0869565217,
						2,
						0
					],
					[
						49956.5217391304,
						2,
						0
					]
				],
				"mustHitSection": false
			},
			{
				"lengthInSteps": 16,
				"sectionNotes": [
					[
						50086.9565217391,
						4,
						0
					],
					[
						50217.3913043478,
						4,
						0
					],
					[
						50347.8260869565,
						4,
						0
					],
					[
						50478.2608695652,
						4,
						0
					],
					[
						50608.6956521739,
						5,
						391.304347826087
					],
					[
						51130.4347826087,
						0,
						0
					],
					[
						51260.8695652174,
						0,
						0
					],
					[
						51391.3043478261,
						0,
						0
					],
					[
						51521.7391304348,
						0,
						0
					],
					[
						52043.4782608696,
						3,
						0
					],
					[
						51913.0434782609,
						3,
						0
					],
					[
						51782.6086956522,
						3,
						0
					],
					[
						51652.1739130435,
						3,
						0
					]
				],
				"mustHitSection": true
			},
			{
				"lengthInSteps": 16,
				"sectionNotes": [
					[
						52173.9130434782,
						2,
						0
					],
					[
						52304.3478260869,
						2,
						0
					],
					[
						52434.7826086956,
						2,
						0
					],
					[
						52565.2173913043,
						2,
						0
					],
					[
						52695.652173913,
						1,
						391.304347826087
					],
					[
						53217.3913043478,
						0,
						0
					],
					[
						53347.8260869565,
						0,
						0
					],
					[
						53478.2608695652,
						0,
						0
					],
					[
						53608.6956521739,
						0,
						0
					],
					[
						53739.1304347826,
						2,
						0
					],
					[
						53869.5652173913,
						2,
						0
					],
					[
						54000,
						2,
						0
					],
					[
						54130.4347826087,
						2,
						0
					]
				],
				"mustHitSection": true
			},
			{
				"lengthInSteps": 16,
				"sectionNotes": [
					[
						55304.347826087,
						2,
						0
					],
					[
						55565.2173913044,
						2,
						0
					],
					[
						55826.0869565218,
						1,
						0
					],
					[
						55956.5217391305,
						1,
						0
					],
					[
						55888.0434782609,
						2,
						0
					],
					[
						56015.2173913044,
						2,
						130.434782608696
					],
					[
						54652.1739130435,
						5,
						0
					],
					[
						54521.7391304348,
						5,
						0
					],
					[
						54391.3043478261,
						5,
						0
					],
					[
						54260.8695652174,
						5,
						0
					],
					[
						54782.6086956522,
						7,
						391.304347826087
					]
				],
				"mustHitSection": false
			},
			{
				"lengthInSteps": 16,
				"sectionNotes": [
					[
						56347.8260869565,
						3,
						0
					],
					[
						56347.8260869565,
						0,
						0
					],
					[
						56608.6956521739,
						0,
						0
					],
					[
						56608.6956521739,
						3,
						0
					],
					[
						56869.5652173913,
						2,
						260.869565217391
					],
					[
						57391.3043478261,
						3,
						0
					],
					[
						57521.7391304348,
						1,
						0
					],
					[
						57652.1739130435,
						3,
						0
					],
					[
						57782.6086956522,
						1,
						0
					],
					[
						57913.0434782609,
						2,
						130.434782608696
					],
					[
						58173.9130434783,
						2,
						130.434782608696
					]
				],
				"mustHitSection": false
			},
			{
				"lengthInSteps": 16,
				"sectionNotes": [
					[
						58434.7826086957,
						7,
						260.869565217391
					],
					[
						58434.7826086957,
						2,
						0
					],
					[
						58695.6521739131,
						2,
						0
					],
					[
						58956.5217391305,
						1,
						0
					],
					[
						59086.9565217392,
						1,
						0
					],
					[
						59015.2173913044,
						2,
						0
					],
					[
						59145.6521739131,
						2,
						130.434782608696
					],
					[
						59478.2608695652,
						1,
						0
					],
					[
						59739.1304347826,
						1,
						0
					],
					[
						60000,
						1,
						260.869565217391
					]
				],
				"mustHitSection": true
			},
			{
				"lengthInSteps": 16,
				"sectionNotes": [
					[
						60521.7391304348,
						1,
						0
					],
					[
						60652.1739130435,
						3,
						0
					],
					[
						60782.6086956522,
						1,
						0
					],
					[
						60913.0434782609,
						3,
						0
					],
					[
						61043.4782608696,
						2,
						130.434782608696
					],
					[
						61304.347826087,
						2,
						130.434782608696
					],
					[
						61565.2173913044,
						2,
						260.869565217391
					]
				],
				"mustHitSection": true
			},
			{
				"lengthInSteps": 16,
				"sectionNotes": [],
				"mustHitSection": false
			},
			{
				"lengthInSteps": 16,
				"sectionNotes": [],
				"mustHitSection": true
			},
			{
				"sectionNotes": [],
				"typeOfSection": 0,
				"lengthInSteps": 16,
				"altAnim": false,
				"mustHitSection": true,
				"changeBPM": false,
				"bpm": 100
			},
			{
				"sectionNotes": [],
				"typeOfSection": 0,
				"lengthInSteps": 16,
				"altAnim": false,
				"mustHitSection": true,
				"changeBPM": false,
				"bpm": 100
			},
			{
				"sectionNotes": [],
				"typeOfSection": 0,
				"lengthInSteps": 16,
				"altAnim": false,
				"mustHitSection": true,
				"changeBPM": false,
				"bpm": 100
			},
			{
				"lengthInSteps": 16,
				"typeOfSection": 0,
				"sectionNotes": [],
				"altAnim": false,
				"bpm": 100,
				"changeBPM": false,
				"mustHitSection": true
			},
			{
				"lengthInSteps": 16,
				"typeOfSection": 0,
				"sectionNotes": [],
				"altAnim": false,
				"bpm": 100,
				"changeBPM": false,
				"mustHitSection": true
			},
			{
				"lengthInSteps": 16,
				"typeOfSection": 0,
				"sectionNotes": [],
				"altAnim": false,
				"bpm": 100,
				"changeBPM": false,
				"mustHitSection": true
			},
			{
				"sectionNotes": [],
				"typeOfSection": 0,
				"lengthInSteps": 16,
				"gfSection": false,
				"altAnim": false,
				"mustHitSection": true,
				"changeBPM": false,
				"bpm": 100
			},
			{
				"sectionNotes": [],
				"typeOfSection": 0,
				"lengthInSteps": 16,
				"gfSection": false,
				"altAnim": false,
				"mustHitSection": true,
				"changeBPM": false,
				"bpm": 115
			},
			{
				"sectionNotes": [],
				"typeOfSection": 0,
				"lengthInSteps": 16,
				"gfSection": false,
				"altAnim": false,
				"mustHitSection": true,
				"changeBPM": false,
				"bpm": 115
			},
			{
				"sectionNotes": [],
				"typeOfSection": 0,
				"lengthInSteps": 16,
				"gfSection": false,
				"altAnim": false,
				"mustHitSection": true,
				"changeBPM": false,
				"bpm": 115
			},
			{
				"sectionNotes": [],
				"typeOfSection": 0,
				"lengthInSteps": 16,
				"gfSection": false,
				"altAnim": false,
				"mustHitSection": true,
				"changeBPM": false,
				"bpm": 115
			},
			{
				"sectionNotes": [],
				"typeOfSection": 0,
				"lengthInSteps": 16,
				"gfSection": false,
				"altAnim": false,
				"mustHitSection": true,
				"changeBPM": false,
				"bpm": 115
			},
			{
				"lengthInSteps": 16,
				"typeOfSection": 0,
				"sectionNotes": [],
				"altAnim": false,
				"gfSection": false,
				"bpm": 115,
				"changeBPM": false,
				"mustHitSection": true
			},
			{
				"lengthInSteps": 16,
				"typeOfSection": 0,
				"sectionNotes": [],
				"altAnim": false,
				"gfSection": false,
				"bpm": 115,
				"changeBPM": false,
				"mustHitSection": true
			},
			{
				"sectionNotes": [],
				"typeOfSection": 0,
				"lengthInSteps": 16,
				"gfSection": false,
				"altAnim": false,
				"mustHitSection": true,
				"changeBPM": false,
				"bpm": 115
			},
			{
				"sectionNotes": [],
				"typeOfSection": 0,
				"lengthInSteps": 16,
				"gfSection": false,
				"altAnim": false,
				"mustHitSection": true,
				"changeBPM": false,
				"bpm": 115
			},
			{
				"sectionNotes": [],
				"typeOfSection": 0,
				"lengthInSteps": 16,
				"gfSection": false,
				"altAnim": false,
				"mustHitSection": true,
				"changeBPM": false,
				"bpm": 115
			},
			{
				"sectionNotes": [],
				"typeOfSection": 0,
				"lengthInSteps": 16,
				"gfSection": false,
				"altAnim": false,
				"mustHitSection": true,
				"changeBPM": false,
				"bpm": 115
			},
			{
				"sectionNotes": [],
				"typeOfSection": 0,
				"lengthInSteps": 16,
				"gfSection": false,
				"altAnim": false,
				"mustHitSection": true,
				"changeBPM": false,
				"bpm": 115
			},
			{
				"sectionNotes": [],
				"typeOfSection": 0,
				"lengthInSteps": 16,
				"gfSection": false,
				"altAnim": false,
				"mustHitSection": true,
				"changeBPM": false,
				"bpm": 115
			},
			{
				"lengthInSteps": 16,
				"typeOfSection": 0,
				"sectionNotes": [],
				"altAnim": false,
				"gfSection": false,
				"bpm": 115,
				"changeBPM": false,
				"mustHitSection": true
			},
			{
				"lengthInSteps": 16,
				"typeOfSection": 0,
				"sectionNotes": [],
				"altAnim": false,
				"gfSection": false,
				"bpm": 115,
				"changeBPM": false,
				"mustHitSection": true
			},
			{
				"sectionNotes": [],
				"typeOfSection": 0,
				"lengthInSteps": 16,
				"gfSection": false,
				"altAnim": false,
				"mustHitSection": true,
				"changeBPM": false,
				"bpm": 115
			},
			{
				"sectionNotes": [],
				"typeOfSection": 0,
				"lengthInSteps": 16,
				"gfSection": false,
				"altAnim": false,
				"mustHitSection": true,
				"changeBPM": false,
				"bpm": 115
			},
			{
				"gfSection": false,
				"lengthInSteps": 16,
				"altAnim": false,
				"typeOfSection": 0,
				"sectionNotes": [],
				"bpm": 115,
				"changeBPM": false,
				"mustHitSection": true
			}
		],
		"gfVersion": "gf",
		"events": [],
		"player3": null,
		"song": "Cursed",
		"validScore": true,
		"needsVoices": true,
		"stage": "store1",
		"speed": 1.9,
		"bpm": 115
	}
}